{
  "O' Romeo": {
    "shows": 599,
    "gross": 2995728.19,
    "sold": 11374,
    "totalSeats": 130886,
    "venues": 205,
    "cities": 119,
    "fastfilling": 12,
    "housefull": 3,
    "occupancy": 8.69
  },
  "Pennum Porattum": {
    "shows": 5,
    "gross": 7395.8,
    "sold": 48,
    "totalSeats": 781,
    "venues": 5,
    "cities": 5,
    "fastfilling": 0,
    "housefull": 0,
    "occupancy": 6.15
  },
  "Nilave": {
    "shows": 8,
    "gross": 30117.0,
    "sold": 205,
    "totalSeats": 2731,
    "venues": 5,
    "cities": 5,
    "fastfilling": 0,
    "housefull": 0,
    "occupancy": 7.51
  },
  "Amaravathiki Aahvanam": {
    "shows": 14,
    "gross": 82126.0,
    "sold": 1215,
    "totalSeats": 4378,
    "venues": 7,
    "cities": 7,
    "fastfilling": 3,
    "housefull": 0,
    "occupancy": 27.75
  },
  "Crime 101": {
    "shows": 44,
    "gross": 154572.12,
    "sold": 458,
    "totalSeats": 7842,
    "venues": 30,
    "cities": 20,
    "fastfilling": 0,
    "housefull": 1,
    "occupancy": 5.84
  },
  "My Lord": {
    "shows": 59,
    "gross": 148745.28,
    "sold": 1164,
    "totalSeats": 23466,
    "venues": 28,
    "cities": 12,
    "fastfilling": 0,
    "housefull": 0,
    "occupancy": 4.96
  },
  "With Love": {
    "shows": 57,
    "gross": 285893.56,
    "sold": 1963,
    "totalSeats": 18772,
    "venues": 32,
    "cities": 17,
    "fastfilling": 2,
    "housefull": 0,
    "occupancy": 10.46
  },
  "Border 2": {
    "shows": 108,
    "gross": 335241.0,
    "sold": 1863,
    "totalSeats": 19382,
    "venues": 76,
    "cities": 41,
    "fastfilling": 2,
    "housefull": 0,
    "occupancy": 9.61
  },
  "Prakambanam": {
    "shows": 20,
    "gross": 85736.98,
    "sold": 510,
    "totalSeats": 3753,
    "venues": 14,
    "cities": 11,
    "fastfilling": 1,
    "housefull": 0,
    "occupancy": 13.59
  },
  "DSP Dev 2": {
    "shows": 30,
    "gross": 120490.0,
    "sold": 534,
    "totalSeats": 6181,
    "venues": 12,
    "cities": 7,
    "fastfilling": 0,
    "housefull": 0,
    "occupancy": 8.64
  },
  "Bebe Main Badmash Banuga?": {
    "shows": 3,
    "gross": 16110.0,
    "sold": 62,
    "totalSeats": 568,
    "venues": 2,
    "cities": 1,
    "fastfilling": 0,
    "housefull": 0,
    "occupancy": 10.92
  },
  "Tu Yaa Main": {
    "shows": 94,
    "gross": 279898.73,
    "sold": 1010,
    "totalSeats": 18922,
    "venues": 47,
    "cities": 24,
    "fastfilling": 0,
    "housefull": 0,
    "occupancy": 5.34
  },
  "Euphoria": {
    "shows": 2,
    "gross": 2500.0,
    "sold": 22,
    "totalSeats": 567,
    "venues": 2,
    "cities": 2,
    "fastfilling": 0,
    "housefull": 0,
    "occupancy": 3.88
  },
  "Funky": {
    "shows": 80,
    "gross": 691412.12,
    "sold": 5045,
    "totalSeats": 26328,
    "venues": 39,
    "cities": 33,
    "fastfilling": 9,
    "housefull": 0,
    "occupancy": 19.16
  },
  "Wuthering Heights": {
    "shows": 35,
    "gross": 175387.58,
    "sold": 559,
    "totalSeats": 6790,
    "venues": 20,
    "cities": 13,
    "fastfilling": 0,
    "housefull": 0,
    "occupancy": 8.23
  },
  "Kaa -The Forest": {
    "shows": 10,
    "gross": 3350.0,
    "sold": 15,
    "totalSeats": 1717,
    "venues": 6,
    "cities": 3,
    "fastfilling": 0,
    "housefull": 0,
    "occupancy": 0.87
  },
  "Sweety Naughty Crazy": {
    "shows": 7,
    "gross": 21850.0,
    "sold": 175,
    "totalSeats": 2240,
    "venues": 3,
    "cities": 2,
    "fastfilling": 0,
    "housefull": 0,
    "occupancy": 7.81
  },
  "Pookie": {
    "shows": 26,
    "gross": 51694.9,
    "sold": 332,
    "totalSeats": 8281,
    "venues": 15,
    "cities": 6,
    "fastfilling": 0,
    "housefull": 0,
    "occupancy": 4.01
  },
  "Saiyaara": {
    "shows": 3,
    "gross": 1761.0,
    "sold": 17,
    "totalSeats": 407,
    "venues": 2,
    "cities": 2,
    "fastfilling": 0,
    "housefull": 0,
    "occupancy": 4.18
  },
  "Rakkasapuradol": {
    "shows": 13,
    "gross": 27130.0,
    "sold": 117,
    "totalSeats": 3442,
    "venues": 8,
    "cities": 6,
    "fastfilling": 0,
    "housefull": 0,
    "occupancy": 3.4
  },
  "Mardaani 3": {
    "shows": 58,
    "gross": 201152.0,
    "sold": 755,
    "totalSeats": 9652,
    "venues": 40,
    "cities": 25,
    "fastfilling": 0,
    "housefull": 0,
    "occupancy": 7.82
  },
  "Punha Ekda Sade Made Teen": {
    "shows": 25,
    "gross": 71688.0,
    "sold": 301,
    "totalSeats": 4547,
    "venues": 14,
    "cities": 4,
    "fastfilling": 0,
    "housefull": 0,
    "occupancy": 6.62
  },
  "Krantijyoti Vidyalay Marathi Madhyam": {
    "shows": 4,
    "gross": 26650.0,
    "sold": 102,
    "totalSeats": 353,
    "venues": 3,
    "cities": 1,
    "fastfilling": 1,
    "housefull": 0,
    "occupancy": 28.9
  },
  "Vadh 2": {
    "shows": 2,
    "gross": 7140.0,
    "sold": 24,
    "totalSeats": 116,
    "venues": 2,
    "cities": 1,
    "fastfilling": 0,
    "housefull": 0,
    "occupancy": 20.69
  },
  "Sirai": {
    "shows": 2,
    "gross": 8410.0,
    "sold": 44,
    "totalSeats": 374,
    "venues": 1,
    "cities": 1,
    "fastfilling": 0,
    "housefull": 0,
    "occupancy": 11.76
  },
  "Minnale": {
    "shows": 14,
    "gross": 29496.84,
    "sold": 261,
    "totalSeats": 3979,
    "venues": 10,
    "cities": 4,
    "fastfilling": 0,
    "housefull": 0,
    "occupancy": 6.56
  },
  "Jockey": {
    "shows": 1,
    "gross": 370.0,
    "sold": 4,
    "totalSeats": 198,
    "venues": 1,
    "cities": 1,
    "fastfilling": 0,
    "housefull": 0,
    "occupancy": 2.02
  },
  "Hot Spot 2 Much": {
    "shows": 4,
    "gross": 5630.0,
    "sold": 31,
    "totalSeats": 859,
    "venues": 2,
    "cities": 1,
    "fastfilling": 0,
    "housefull": 0,
    "occupancy": 3.61
  },
  "AT: Welcome to the Dark Side": {
    "shows": 8,
    "gross": 22200.0,
    "sold": 103,
    "totalSeats": 2853,
    "venues": 8,
    "cities": 6,
    "fastfilling": 0,
    "housefull": 0,
    "occupancy": 3.61
  },
  "Koodothram": {
    "shows": 3,
    "gross": 2640.0,
    "sold": 15,
    "totalSeats": 649,
    "venues": 3,
    "cities": 3,
    "fastfilling": 0,
    "housefull": 0,
    "occupancy": 2.31
  },
  "Sukhamano Sukhamann": {
    "shows": 15,
    "gross": 52138.0,
    "sold": 335,
    "totalSeats": 4133,
    "venues": 8,
    "cities": 6,
    "fastfilling": 1,
    "housefull": 0,
    "occupancy": 8.11
  },
  "Ashakal Aayiram": {
    "shows": 22,
    "gross": 88001.46,
    "sold": 594,
    "totalSeats": 5411,
    "venues": 16,
    "cities": 12,
    "fastfilling": 1,
    "housefull": 0,
    "occupancy": 10.98
  },
  "Mana Shankara Vara Prasad Garu": {
    "shows": 15,
    "gross": 24456.0,
    "sold": 251,
    "totalSeats": 4839,
    "venues": 12,
    "cities": 12,
    "fastfilling": 0,
    "housefull": 0,
    "occupancy": 5.19
  },
  "Uyirullavarai Usha": {
    "shows": 9,
    "gross": 21790.0,
    "sold": 164,
    "totalSeats": 2087,
    "venues": 5,
    "cities": 3,
    "fastfilling": 0,
    "housefull": 0,
    "occupancy": 7.86
  },
  "Anomie: The Equation of Death": {
    "shows": 6,
    "gross": 34153.1,
    "sold": 208,
    "totalSeats": 1308,
    "venues": 5,
    "cities": 3,
    "fastfilling": 0,
    "housefull": 0,
    "occupancy": 15.9
  },
  "Veeram (Tamil)": {
    "shows": 4,
    "gross": 0.0,
    "sold": 0,
    "totalSeats": 815,
    "venues": 2,
    "cities": 2,
    "fastfilling": 0,
    "housefull": 0,
    "occupancy": 0.0
  },
  "Sky (2026)": {
    "shows": 5,
    "gross": 49614.0,
    "sold": 732,
    "totalSeats": 1416,
    "venues": 4,
    "cities": 4,
    "fastfilling": 2,
    "housefull": 0,
    "occupancy": 51.69
  },
  "Aga Aga Sunbai! Kay Mhantay Sasubai?": {
    "shows": 7,
    "gross": 16180.0,
    "sold": 86,
    "totalSeats": 847,
    "venues": 6,
    "cities": 3,
    "fastfilling": 0,
    "housefull": 0,
    "occupancy": 10.15
  },
  "Mounam Pesiyadhe": {
    "shows": 6,
    "gross": 20525.04,
    "sold": 173,
    "totalSeats": 1459,
    "venues": 6,
    "cities": 3,
    "fastfilling": 0,
    "housefull": 0,
    "occupancy": 11.86
  },
  "Ranapati Shivray - Swari Agra": {
    "shows": 3,
    "gross": 11740.0,
    "sold": 46,
    "totalSeats": 691,
    "venues": 3,
    "cities": 2,
    "fastfilling": 0,
    "housefull": 0,
    "occupancy": 6.66
  },
  "Mon Maaney Na": {
    "shows": 6,
    "gross": 12000.0,
    "sold": 62,
    "totalSeats": 1363,
    "venues": 6,
    "cities": 3,
    "fastfilling": 0,
    "housefull": 0,
    "occupancy": 4.55
  },
  "Spa": {
    "shows": 9,
    "gross": 13290.0,
    "sold": 78,
    "totalSeats": 2577,
    "venues": 6,
    "cities": 4,
    "fastfilling": 0,
    "housefull": 0,
    "occupancy": 3.03
  },
  "Amruthaanjan": {
    "shows": 4,
    "gross": 800.0,
    "sold": 4,
    "totalSeats": 3420,
    "venues": 2,
    "cities": 2,
    "fastfilling": 0,
    "housefull": 0,
    "occupancy": 0.12
  },
  "Bara Badhu": {
    "shows": 8,
    "gross": 6780.0,
    "sold": 28,
    "totalSeats": 929,
    "venues": 6,
    "cities": 6,
    "fastfilling": 0,
    "housefull": 0,
    "occupancy": 3.01
  },
  "Dhurandhar": {
    "shows": 4,
    "gross": 17653.0,
    "sold": 57,
    "totalSeats": 313,
    "venues": 4,
    "cities": 3,
    "fastfilling": 0,
    "housefull": 0,
    "occupancy": 18.21
  },
  "AataChakki": {
    "shows": 6,
    "gross": 300.0,
    "sold": 2,
    "totalSeats": 1269,
    "venues": 3,
    "cities": 3,
    "fastfilling": 0,
    "housefull": 0,
    "occupancy": 0.16
  },
  "Ee Thaniniram": {
    "shows": 2,
    "gross": 2835.0,
    "sold": 21,
    "totalSeats": 951,
    "venues": 2,
    "cities": 2,
    "fastfilling": 0,
    "housefull": 0,
    "occupancy": 2.21
  },
  "Mylanji": {
    "shows": 4,
    "gross": 4695.0,
    "sold": 33,
    "totalSeats": 680,
    "venues": 4,
    "cities": 2,
    "fastfilling": 0,
    "housefull": 0,
    "occupancy": 4.85
  },
  "Valathu Vasathe Kallan": {
    "shows": 2,
    "gross": 10180.0,
    "sold": 73,
    "totalSeats": 1134,
    "venues": 2,
    "cities": 2,
    "fastfilling": 0,
    "housefull": 0,
    "occupancy": 6.44
  },
  "Sunny Di Honey": {
    "shows": 5,
    "gross": 30390.0,
    "sold": 134,
    "totalSeats": 890,
    "venues": 4,
    "cities": 2,
    "fastfilling": 0,
    "housefull": 0,
    "occupancy": 15.06
  },
  "Joker": {
    "shows": 1,
    "gross": 7950.0,
    "sold": 22,
    "totalSeats": 269,
    "venues": 1,
    "cities": 1,
    "fastfilling": 0,
    "housefull": 0,
    "occupancy": 8.18
  },
  "O Sundara Rakshasi": {
    "shows": 1,
    "gross": 6800.0,
    "sold": 28,
    "totalSeats": 97,
    "venues": 1,
    "cities": 1,
    "fastfilling": 0,
    "housefull": 0,
    "occupancy": 28.87
  },
  "Landlord": {
    "shows": 3,
    "gross": 6600.0,
    "sold": 18,
    "totalSeats": 1306,
    "venues": 2,
    "cities": 2,
    "fastfilling": 0,
    "housefull": 0,
    "occupancy": 1.38
  },
  "Kariya": {
    "shows": 3,
    "gross": 2500.0,
    "sold": 11,
    "totalSeats": 509,
    "venues": 3,
    "cities": 3,
    "fastfilling": 0,
    "housefull": 0,
    "occupancy": 2.16
  },
  "Couple Friendly": {
    "shows": 1,
    "gross": 4000.0,
    "sold": 8,
    "totalSeats": 64,
    "venues": 1,
    "cities": 1,
    "fastfilling": 0,
    "housefull": 0,
    "occupancy": 12.5
  },
  "Chatha Pacha: The Ring of Rowdies": {
    "shows": 4,
    "gross": 2520.0,
    "sold": 14,
    "totalSeats": 800,
    "venues": 4,
    "cities": 4,
    "fastfilling": 0,
    "housefull": 0,
    "occupancy": 1.75
  },
  "Anaganaga Oka Raju": {
    "shows": 1,
    "gross": 5800.0,
    "sold": 58,
    "totalSeats": 282,
    "venues": 1,
    "cities": 1,
    "fastfilling": 0,
    "housefull": 0,
    "occupancy": 20.57
  },
  "Man Aatale Manaatale": {
    "shows": 2,
    "gross": 2240.0,
    "sold": 8,
    "totalSeats": 210,
    "venues": 2,
    "cities": 2,
    "fastfilling": 0,
    "housefull": 0,
    "occupancy": 3.81
  },
  "Lagan Laagii Re": {
    "shows": 7,
    "gross": 300.0,
    "sold": 2,
    "totalSeats": 1154,
    "venues": 5,
    "cities": 4,
    "fastfilling": 0,
    "housefull": 0,
    "occupancy": 0.17
  },
  "Master Mind (2026)": {
    "shows": 1,
    "gross": 0.0,
    "sold": 0,
    "totalSeats": 189,
    "venues": 1,
    "cities": 1,
    "fastfilling": 0,
    "housefull": 0,
    "occupancy": 0.0
  },
  "Vijaynagar'er Hirey (Kakababu)": {
    "shows": 1,
    "gross": 1750.0,
    "sold": 9,
    "totalSeats": 256,
    "venues": 1,
    "cities": 1,
    "fastfilling": 0,
    "housefull": 0,
    "occupancy": 3.52
  },
  "Aashaan": {
    "shows": 2,
    "gross": 13130.0,
    "sold": 101,
    "totalSeats": 877,
    "venues": 1,
    "cities": 1,
    "fastfilling": 0,
    "housefull": 0,
    "occupancy": 11.52
  },
  "Kattemar": {
    "shows": 3,
    "gross": 2739.0,
    "sold": 22,
    "totalSeats": 360,
    "venues": 2,
    "cities": 2,
    "fastfilling": 0,
    "housefull": 0,
    "occupancy": 6.11
  },
  "Rakta Golapa": {
    "shows": 3,
    "gross": 4370.0,
    "sold": 19,
    "totalSeats": 278,
    "venues": 3,
    "cities": 3,
    "fastfilling": 0,
    "housefull": 0,
    "occupancy": 6.83
  },
  "Bhartha Mahasayulaku Wignyapthi": {
    "shows": 1,
    "gross": 0.0,
    "sold": 0,
    "totalSeats": 99,
    "venues": 1,
    "cities": 1,
    "fastfilling": 0,
    "housefull": 0,
    "occupancy": 0.0
  },
  "Marali Manasaagide": {
    "shows": 1,
    "gross": 2340.0,
    "sold": 18,
    "totalSeats": 79,
    "venues": 1,
    "cities": 1,
    "fastfilling": 0,
    "housefull": 0,
    "occupancy": 22.78
  },
  "Yeh Dil Aashiqanaa": {
    "shows": 8,
    "gross": 21709.0,
    "sold": 97,
    "totalSeats": 766,
    "venues": 7,
    "cities": 6,
    "fastfilling": 0,
    "housefull": 1,
    "occupancy": 12.66
  },
  "Man Aatle Mantle": {
    "shows": 2,
    "gross": 1180.0,
    "sold": 10,
    "totalSeats": 293,
    "venues": 2,
    "cities": 2,
    "fastfilling": 0,
    "housefull": 0,
    "occupancy": 3.41
  },
  "Therincha Kadhalinga": {
    "shows": 2,
    "gross": 4760.0,
    "sold": 36,
    "totalSeats": 365,
    "venues": 2,
    "cities": 2,
    "fastfilling": 0,
    "housefull": 0,
    "occupancy": 9.86
  },
  "Dilwale Dulhania Le Jayenge": {
    "shows": 4,
    "gross": 5855.0,
    "sold": 53,
    "totalSeats": 768,
    "venues": 4,
    "cities": 2,
    "fastfilling": 0,
    "housefull": 0,
    "occupancy": 6.9
  },
  "1+1 Offer": {
    "shows": 1,
    "gross": 1575.0,
    "sold": 15,
    "totalSeats": 167,
    "venues": 1,
    "cities": 1,
    "fastfilling": 0,
    "housefull": 0,
    "occupancy": 8.98
  },
  "Demon Slayer: Kimetsu no Yaiba Infinity Castle": {
    "shows": 1,
    "gross": 2850.0,
    "sold": 19,
    "totalSeats": 55,
    "venues": 1,
    "cities": 1,
    "fastfilling": 0,
    "housefull": 0,
    "occupancy": 34.55
  },
  "Avatar: Fire and Ash": {
    "shows": 2,
    "gross": 8756.0,
    "sold": 30,
    "totalSeats": 351,
    "venues": 2,
    "cities": 2,
    "fastfilling": 0,
    "housefull": 0,
    "occupancy": 8.55
  },
  "Roller Coaster 2, Terrific Dinosaurs, Adventure of an Iceberg (7D)": {
    "shows": 3,
    "gross": 0.0,
    "sold": 0,
    "totalSeats": 36,
    "venues": 1,
    "cities": 1,
    "fastfilling": 0,
    "housefull": 0,
    "occupancy": 0.0
  },
  "Prehistoric Adventure 7D, Scary House, Polar Roller Coaster (7D)": {
    "shows": 3,
    "gross": 0.0,
    "sold": 0,
    "totalSeats": 36,
    "venues": 1,
    "cities": 1,
    "fastfilling": 0,
    "housefull": 0,
    "occupancy": 0.0
  },
  "Lost in Fear, Ride in the Mines, Tomb of Pharaoh 1 (7D)": {
    "shows": 3,
    "gross": 0.0,
    "sold": 0,
    "totalSeats": 36,
    "venues": 1,
    "cities": 1,
    "fastfilling": 0,
    "housefull": 0,
    "occupancy": 0.0
  },
  "Veer Zaara": {
    "shows": 3,
    "gross": 4580.0,
    "sold": 32,
    "totalSeats": 471,
    "venues": 3,
    "cities": 2,
    "fastfilling": 0,
    "housefull": 0,
    "occupancy": 6.79
  },
  "The Housemaid": {
    "shows": 1,
    "gross": 4250.0,
    "sold": 8,
    "totalSeats": 25,
    "venues": 1,
    "cities": 1,
    "fastfilling": 0,
    "housefull": 0,
    "occupancy": 32.0
  },
  "Marty Supreme": {
    "shows": 1,
    "gross": 1160.0,
    "sold": 2,
    "totalSeats": 49,
    "venues": 1,
    "cities": 1,
    "fastfilling": 0,
    "housefull": 0,
    "occupancy": 4.08
  },
  "Bihu Attack": {
    "shows": 2,
    "gross": 0.0,
    "sold": 0,
    "totalSeats": 280,
    "venues": 1,
    "cities": 1,
    "fastfilling": 0,
    "housefull": 0,
    "occupancy": 0.0
  },
  "Bhanupriya Bhooter Hotel": {
    "shows": 1,
    "gross": 0.0,
    "sold": 0,
    "totalSeats": 327,
    "venues": 1,
    "cities": 1,
    "fastfilling": 0,
    "housefull": 0,
    "occupancy": 0.0
  },
  "Non Veg": {
    "shows": 1,
    "gross": 99.0,
    "sold": 1,
    "totalSeats": 124,
    "venues": 1,
    "cities": 1,
    "fastfilling": 0,
    "housefull": 0,
    "occupancy": 0.81
  },
  "Jai": {
    "shows": 1,
    "gross": 0.0,
    "sold": 0,
    "totalSeats": 129,
    "venues": 1,
    "cities": 1,
    "fastfilling": 0,
    "housefull": 0,
    "occupancy": 0.0
  },
  "Rama and Ramu": {
    "shows": 1,
    "gross": 1250.0,
    "sold": 4,
    "totalSeats": 97,
    "venues": 1,
    "cities": 1,
    "fastfilling": 0,
    "housefull": 0,
    "occupancy": 4.12
  },
  "*Star": {
    "shows": 1,
    "gross": 2800.0,
    "sold": 8,
    "totalSeats": 97,
    "venues": 1,
    "cities": 1,
    "fastfilling": 0,
    "housefull": 0,
    "occupancy": 8.25
  },
  "Gharga": {
    "shows": 1,
    "gross": 0.0,
    "sold": 0,
    "totalSeats": 97,
    "venues": 1,
    "cities": 1,
    "fastfilling": 0,
    "housefull": 0,
    "occupancy": 0.0
  },
  "Daiva": {
    "shows": 1,
    "gross": 2800.0,
    "sold": 8,
    "totalSeats": 97,
    "venues": 1,
    "cities": 1,
    "fastfilling": 0,
    "housefull": 0,
    "occupancy": 8.25
  },
  "Juniors Journey": {
    "shows": 2,
    "gross": 0.0,
    "sold": 0,
    "totalSeats": 393,
    "venues": 2,
    "cities": 2,
    "fastfilling": 0,
    "housefull": 0,
    "occupancy": 0.0
  },
  "Mohabbatein ": {
    "shows": 1,
    "gross": 0.0,
    "sold": 0,
    "totalSeats": 24,
    "venues": 1,
    "cities": 1,
    "fastfilling": 0,
    "housefull": 0,
    "occupancy": 0.0
  },
  "Dream Girl (2026)": {
    "shows": 1,
    "gross": 18850.8,
    "sold": 130,
    "totalSeats": 130,
    "venues": 1,
    "cities": 1,
    "fastfilling": 0,
    "housefull": 1,
    "occupancy": 100.0
  },
  "Orange": {
    "shows": 1,
    "gross": 0.0,
    "sold": 0,
    "totalSeats": 39,
    "venues": 1,
    "cities": 1,
    "fastfilling": 0,
    "housefull": 0,
    "occupancy": 0.0
  },
  "Zootopia 2": {
    "shows": 2,
    "gross": 4000.0,
    "sold": 18,
    "totalSeats": 159,
    "venues": 2,
    "cities": 2,
    "fastfilling": 0,
    "housefull": 0,
    "occupancy": 11.32
  },
  "Ek Deewane Ki Deewaniyat": {
    "shows": 1,
    "gross": 210.0,
    "sold": 2,
    "totalSeats": 102,
    "venues": 1,
    "cities": 1,
    "fastfilling": 0,
    "housefull": 0,
    "occupancy": 1.96
  },
  "Sanam Teri Kasam": {
    "shows": 1,
    "gross": 0.0,
    "sold": 0,
    "totalSeats": 152,
    "venues": 1,
    "cities": 1,
    "fastfilling": 0,
    "housefull": 0,
    "occupancy": 0.0
  }
}